AttentionMechanism/__init__.py
AttentionMechanism/model/__init__.py
AttentionMechanism/model/attention/A2Atttention.py
AttentionMechanism/model/attention/AAAttention.py
AttentionMechanism/model/attention/ACmixAttention.py
AttentionMechanism/model/attention/AFT.py
AttentionMechanism/model/attention/Axial_attention.py
AttentionMechanism/model/attention/BAM.py
AttentionMechanism/model/attention/CBAM.py
AttentionMechanism/model/attention/CoAtNet.py
AttentionMechanism/model/attention/CoTAttention.py
AttentionMechanism/model/attention/CoordAttention.py
AttentionMechanism/model/attention/CrissCrossAttention.py
AttentionMechanism/model/attention/Crossformer.py
AttentionMechanism/model/attention/DANet.py
AttentionMechanism/model/attention/DAT.py
AttentionMechanism/model/attention/ECAAttention.py
AttentionMechanism/model/attention/EMSA.py
AttentionMechanism/model/attention/ExternalAttention.py
AttentionMechanism/model/attention/FCA.py
AttentionMechanism/model/attention/GCAttention.py
AttentionMechanism/model/attention/GCTAttention.py
AttentionMechanism/model/attention/GaussianAttention.py
AttentionMechanism/model/attention/HaloAttention.py
AttentionMechanism/model/attention/LCTAttention.py
AttentionMechanism/model/attention/MOATransformer.py
AttentionMechanism/model/attention/MUSEAttention.py
AttentionMechanism/model/attention/MobileViTAttention.py
AttentionMechanism/model/attention/MobileViTv2Attention.py
AttentionMechanism/model/attention/OutlookAttention.py
AttentionMechanism/model/attention/PSA.py
AttentionMechanism/model/attention/ParNetAttention.py
AttentionMechanism/model/attention/PolarizedSelfAttention.py
AttentionMechanism/model/attention/ResidualAttention.py
AttentionMechanism/model/attention/S2Attention.py
AttentionMechanism/model/attention/SEAttention.py
AttentionMechanism/model/attention/SGE.py
AttentionMechanism/model/attention/SKAttention.py
AttentionMechanism/model/attention/SelfAttention.py
AttentionMechanism/model/attention/ShuffleAttention.py
AttentionMechanism-1.0.2.dist-info/LICENSE
AttentionMechanism-1.0.2.dist-info/METADATA
AttentionMechanism-1.0.2.dist-info/WHEEL
AttentionMechanism-1.0.2.dist-info/top_level.txt
AttentionMechanism-1.0.2.dist-info/RECORD
