Metadata-Version: 2.1
Name: AttentionMechanism
Version: 1.0.2
Summary: This repository contains an implementation of many attention mechanism models.
Home-page: https://github.com/gongyan1/Attention-Mechanism-Pytorch
Author: 
Author-email: 
License: Apache
Keywords: Attention,Machine Learning,Deep Learning,Neural Networks,Pytorch
Classifier: Intended Audience :: Developers
Classifier: Intended Audience :: Education
Classifier: Intended Audience :: Science/Research
Classifier: License :: OSI Approved :: Apache Software License
Classifier: Operating System :: OS Independent
Classifier: Programming Language :: Python :: 3
Classifier: Topic :: Scientific/Engineering :: Artificial Intelligence
Requires-Python: >=3.7.0
License-File: LICENSE
